task_api/__init__.py
task_api/apps.py
task_api/backends/__init__.py
task_api/backends/base.py
task_api/backends/celery.py
task_api/migrations/0001_initial.py
task_api/migrations/__init__.py
task_api/models.py
task_api/params.py
task_api/serializers.py
task_api/static/.gitkeep
task_api/static/django-task-api.min.js
task_api/tasks.py
task_api/urls.py
task_api/utils.py
task_api/views.py
django_task_api-1.4.1.dist-info/LICENSE
django_task_api-1.4.1.dist-info/WHEEL
django_task_api-1.4.1.dist-info/METADATA
django_task_api-1.4.1.dist-info/RECORD
