Metadata-Version: 2.1
Name: django-task-api
Version: 1.4.1
Summary: A REST API for managing background tasks in Django
License: MIT
Author: Nikolas Stevenson-Molnar
Author-email: nik.molnar@consbio.org
Requires-Python: >=3.6,<4.0
Classifier: License :: OSI Approved :: MIT License
Classifier: Programming Language :: Python :: 3
Classifier: Programming Language :: Python :: 3.10
Classifier: Programming Language :: Python :: 3.6
Classifier: Programming Language :: Python :: 3.7
Classifier: Programming Language :: Python :: 3.8
Classifier: Programming Language :: Python :: 3.9
Requires-Dist: Django
Requires-Dist: celery (>=4)
Requires-Dist: djangorestframework (>=3.0,<4.0)
Requires-Dist: six (>=1.16.0,<2.0.0)
